ipyselect2/__init__.py
ipyselect2/_version.py
ipyselect2/select2.py
ipyselect2/static/extension.js
ipyselect2/static/index.js
ipyselect2/static/index.js.map
ipyselect2-0.2.1.data/data/etc/jupyter/nbconfig/notebook.d/ipyselect2.json
ipyselect2-0.2.1.data/data/share/jupyter/nbextensions/ipyselect2/extension.js
ipyselect2-0.2.1.data/data/share/jupyter/nbextensions/ipyselect2/index.js
ipyselect2-0.2.1.data/data/share/jupyter/nbextensions/ipyselect2/index.js.map
ipyselect2-0.2.1.dist-info/LICENSE
ipyselect2-0.2.1.dist-info/METADATA
ipyselect2-0.2.1.dist-info/WHEEL
ipyselect2-0.2.1.dist-info/top_level.txt
ipyselect2-0.2.1.dist-info/RECORD
